Workbook

Sheet START HERE
A1: UAE Freelancer & Small Business Bookkeeping Tracker 2026
A2: VAT + Corporate Tax ready · Excel & Google Sheets compatible
B4: HOW TO USE
B5: 1. Go to Settings and enter your business name, financial-year start, VAT status and your VAT period dates.
B6: 2. Log every invoice you issue in Income (one row per invoice). Choose the VAT treatment from the dropdown — VAT is calculated for you.
B7: 3. Log every business cost in Expenses. Mark whether the input VAT is recoverable (you have a valid tax invoice and the cost is business-related).
B8: 4. Open the VAT Return sheet before each filing: set the period dates and copy the boxes into the FTA EmaraTax portal.
B9: 5. Watch the Dashboard: monthly profit, unpaid invoices, VAT to set aside, and your Corporate Tax estimate update automatically.
B11: LEGEND
B12: Blue text = cells you type into. Black text = formulas (do not edit). Yellow cells = key settings to check.
B13: Rows 4–6 of Income and Expenses contain SAMPLE data. Clear the cell contents of those rows (don't delete the rows) before you start.
B14: Never delete whole rows — clear cell contents instead, so formulas and dropdowns stay intact. Capacity: 500 rows per sheet.
B16: KEY UAE THRESHOLDS BUILT IN (editable in Settings — verify current figures at tax.gov.ae)
B17: • VAT: 5% standard rate. Mandatory registration when taxable supplies exceed AED 375,000 in the past 12 months (or expected in the next 30 days); voluntary from AED 187,500.
... B22: This workbook is a bookkeeping aid, not tax, legal or accounting advice. Figures are estimates based on the settings you enter. Confirm your obligations with the Federal Tax Authority (tax.gov.ae) or a registered tax agent. The author accepts no liability for filings made using this tool.

Sheet Dashboard
A1: =Settings!B4&" — Dashboard" -> Your Business Name — Dashboard
A2: ="Financial year from "&TEXT(FY_START,"dd mmm yyyy")&" · Today: "&TEXT(TODAY(),"dd mmm yyyy") -> Financial year from 01 Jan 2026 · Today: 20 Sep 2026
A4: Money | B4: Revenue YTD (excl. VAT) | C4: Expenses YTD (excl. VAT) | D4: Profit YTD | E4: Cash received YTD | F4: Unpaid invoices (incl. VAT)
B5: =SUMIFS(Income!$F$4:$F$503,Income!$O$4:$O$503,">=1",Income!$O$4:$O$503,"<=12") -> 24500 | C5: =SUMIFS(Expenses!$E$4:$E$503,Expenses!$M$4:$M$503,">=1",Expenses!$M$4:$M$503,"<=12") -> 11400 | D5: =B5-C5 -> 13100 | E5: =OPEN_CASH+SUMIFS(Income!$L$4:$L$503,Income!$O$4:$O$503,">=1",Income!$O$4:$O$503,"<=12")-SUMIFS(Expenses!$J$4:$J$503,Expenses!$M$4:$M$503,">=1",Expenses!$M$4:$M$503,"<=12") -> 9005 | F5: =SUMIFS(Income!$I$4:$I$503,Income!$J$4:$J$503,"Unpaid")+SUMIFS(Income!$I$4:$I$503,Income!$J$4:$J$503,"Partially paid")-SUMIFS(Income!$L$4:$L$503,Income!$J$4:$J$503,"Partially paid") -> 4725
A7: Compliance | B7: Overdue invoices (count) | C7: Net VAT due this period | D7: Corporate Tax estimate (year) | E7: VAT registration status | F7: Profit margin YTD
B8: =COUNTIF(Income!$N$4:$N$503,"OVERDUE") -> 1 | C8: ='VAT Return'!D16 -> 630 | D8: ='Corporate Tax'!B13 -> 0 | E8: =IF('VAT Return'!D20>=VAT_MAND,"Mandatory",IF('VAT Return'!D20>=VAT_VOL,"Voluntary","Below")) -> Below | F8: =IF(B5=0,0,D5/B5) -> 0.53469388
A10: Month | B10: Revenue (excl. VAT) | C10: Expenses (excl. VAT) | D10: Profit | E10: Cash in | F10: Cash out | G10: Output VAT | H10: Recoverable input VAT | I10: Net VAT | J10: Margin
A11: =TEXT(EDATE(FY_START,0),"mmm yyyy") -> Jan 2026 | B11: =SUMIFS(Income!$F$4:$F$503,Income!$O$4:$O$503,1) -> 12000 | C11: =SUMIFS(Expenses!$E$4:$E$503,Expenses!$M$4:$M$503,1) -> 9900 | D11: =B11-C11 -> 2100 | E11: =SUMIFS(Income!$L$4:$L$503,Income!$O$4:$O$503,1) -> 12600 | F11: =SUMIFS(Expenses!$J$4:$J$503,Expenses!$M$4:$M$503,1) -> 10020 | G11: =SUMIFS(Income!$H$4:$H$503,Income!$O$4:$O$503,1) -> 600 | H11: =SUMIFS(Expenses!$I$4:$I$503,Expenses!$M$4:$M$503,1) -> 120 | I11: =G11-H11 -> 480 | J11: =IF(B11=0,0,D11/B11) -> 0.175
A12: =TEXT(EDATE(FY_START,1),"mmm yyyy") -> Feb 2026 | B12: =SUMIFS(Income!$F$4:$F$503,Income!$O$4:$O$503,2) -> 12500 | C12: =SUMIFS(Expenses!$E$4:$E$503,Expenses!$M$4:$M$503,2) -> 1500 | D12: =B12-C12 -> 11000 | E12: =SUMIFS(Income!$L$4:$L$503,Income!$O$4:$O$503,2) -> 8000 | F12: =SUMIFS(Expenses!$J$4:$J$503,Expenses!$M$4:$M$503,2) -> 1575 | G12: =SUMIFS(Income!$H$4:$H$503,Income!$O$4:$O$503,2) -> 225 | H12: =SUMIFS(Expenses!$I$4:$I$503,Expenses!$M$4:$M$503,2) -> 75 | I12: =G12-H12 -> 150 | J12: =IF(B12=0,0,D12/B12) -> 0.88
A13: =TEXT(EDATE(FY_START,2),"mmm yyyy") -> Mar 2026 | B13: =SUMIFS(Income!$F$4:$F$503,Income!$O$4:$O$503,3) -> 0 | C13: =SUMIFS(Expenses!$E$4:$E$503,Expenses!$M$4:$M$503,3) -> 0 | D13: =B13-C13 -> 0 | E13: =SUMIFS(Income!$L$4:$L$503,Income!$O$4:$O$503,3) -> 0 | F13: =SUMIFS(Expenses!$J$4:$J$503,Expenses!$M$4:$M$503,3) -> 0 | G13: =SUMIFS(Income!$H$4:$H$503,Income!$O$4:$O$503,3) -> 0 | H13: =SUMIFS(Expenses!$I$4:$I$503,Expenses!$M$4:$M$503,3) -> 0 | I13: =G13-H13 -> 0 | J13: =IF(B13=0,0,D13/B13) -> 0
A14: =TEXT(EDATE(FY_START,3),"mmm yyyy") -> Apr 2026 | B14: =SUMIFS(Income!$F$4:$F$503,Income!$O$4:$O$503,4) -> 0 | C14: =SUMIFS(Expenses!$E$4:$E$503,Expenses!$M$4:$M$503,4) -> 0 | D14: =B14-C14 -> 0 | E14: =SUMIFS(Income!$L$4:$L$503,Income!$O$4:$O$503,4) -> 0 | F14: =SUMIFS(Expenses!$J$4:$J$503,Expenses!$M$4:$M$503,4) -> 0 | G14: =SUMIFS(Income!$H$4:$H$503,Income!$O$4:$O$503,4) -> 0 | H14: =SUMIFS(Expenses!$I$4:$I$503,Expenses!$M$4:$M$503,4) -> 0 | I14: =G14-H14 -> 0 | J14: =IF(B14=0,0,D14/B14) -> 0
A15: =TEXT(EDATE(FY_START,4),"mmm yyyy") -> May 2026 | B15: =SUMIFS(Income!$F$4:$F$503,Income!$O$4:$O$503,5) -> 0 | C15: =SUMIFS(Expenses!$E$4:$E$503,Expenses!$M$4:$M$503,5) -> 0 | D15: =B15-C15 -> 0 | E15: =SUMIFS(Income!$L$4:$L$503,Income!$O$4:$O$503,5) -> 0 | F15: =SUMIFS(Expenses!$J$4:$J$503,Expenses!$M$4:$M$503,5) -> 0 | G15: =SUMIFS(Income!$H$4:$H$503,Income!$O$4:$O$503,5) -> 0 | H15: =SUMIFS(Expenses!$I$4:$I$503,Expenses!$M$4:$M$503,5) -> 0 | I15: =G15-H15 -> 0 | J15: =IF(B15=0,0,D15/B15) -> 0
A16: =TEXT(EDATE(FY_START,5),"mmm yyyy") -> Jun 2026 | B16: =SUMIFS(Income!$F$4:$F$503,Income!$O$4:$O$503,6) -> 0 | C16: =SUMIFS(Expenses!$E$4:$E$503,Expenses!$M$4:$M$503,6) -> 0 | D16: =B16-C16 -> 0 | E16: =SUMIFS(Income!$L$4:$L$503,Income!$O$4:$O$503,6) -> 0 | F16: =SUMIFS(Expenses!$J$4:$J$503,Expenses!$M$4:$M$503,6) -> 0 | G16: =SUMIFS(Income!$H$4:$H$503,Income!$O$4:$O$503,6) -> 0 | H16: =SUMIFS(Expenses!$I$4:$I$503,Expenses!$M$4:$M$503,6) -> 0 | I16: =G16-H16 -> 0 | J16: =IF(B16=0,0,D16/B16) -> 0
A17: =TEXT(EDATE(FY_START,6),"mmm yyyy") -> Jul 2026 | B17: =SUMIFS(Income!$F$4:$F$503,Income!$O$4:$O$503,7) -> 0 | C17: =SUMIFS(Expenses!$E$4:$E$503,Expenses!$M$4:$M$503,7) -> 0 | D17: =B17-C17 -> 0 | E17: =SUMIFS(Income!$L$4:$L$503,Income!$O$4:$O$503,7) -> 0 | F17: =SUMIFS(Expenses!$J$4:$J$503,Expenses!$M$4:$M$503,7) -> 0 | G17: =SUMIFS(Income!$H$4:$H$503,Income!$O$4:$O$503,7) -> 0 | H17: =SUMIFS(Expenses!$I$4:$I$503,Expenses!$M$4:$M$503,7) -> 0 | I17: =G17-H17 -> 0 | J17: =IF(B17=0,0,D17/B17) -> 0
A18: =TEXT(EDATE(FY_START,7),"mmm yyyy") -> Aug 2026 | B18: =SUMIFS(Income!$F$4:$F$503,Income!$O$4:$O$503,8) -> 0 | C18: =SUMIFS(Expenses!$E$4:$E$503,Expenses!$M$4:$M$503,8) -> 0 | D18: =B18-C18 -> 0 | E18: =SUMIFS(Income!$L$4:$L$503,Income!$O$4:$O$503,8) -> 0 | F18: =SUMIFS(Expenses!$J$4:$J$503,Expenses!$M$4:$M$503,8) -> 0 | G18: =SUMIFS(Income!$H$4:$H$503,Income!$O$4:$O$503,8) -> 0 | H18: =SUMIFS(Expenses!$I$4:$I$503,Expenses!$M$4:$M$503,8) -> 0 | I18: =G18-H18 -> 0 | J18: =IF(B18=0,0,D18/B18) -> 0
A19: =TEXT(EDATE(FY_START,8),"mmm yyyy") -> Sep 2026 | B19: =SUMIFS(Income!$F$4:$F$503,Income!$O$4:$O$503,9) -> 0 | C19: =SUMIFS(Expenses!$E$4:$E$503,Expenses!$M$4:$M$503,9) -> 0 | D19: =B19-C19 -> 0 | E19: =SUMIFS(Income!$L$4:$L$503,Income!$O$4:$O$503,9) -> 0 | F19: =SUMIFS(Expenses!$J$4:$J$503,Expenses!$M$4:$M$503,9) -> 0 | G19: =SUMIFS(Income!$H$4:$H$503,Income!$O$4:$O$503,9) -> 0 | H19: =SUMIFS(Expenses!$I$4:$I$503,Expenses!$M$4:$M$503,9) -> 0 | I19: =G19-H19 -> 0 | J19: =IF(B19=0,0,D19/B19) -> 0
A20: =TEXT(EDATE(FY_START,9),"mmm yyyy") -> Oct 2026 | B20: =SUMIFS(Income!$F$4:$F$503,Income!$O$4:$O$503,10) -> 0 | C20: =SUMIFS(Expenses!$E$4:$E$503,Expenses!$M$4:$M$503,10) -> 0 | D20: =B20-C20 -> 0 | E20: =SUMIFS(Income!$L$4:$L$503,Income!$O$4:$O$503,10) -> 0 | F20: =SUMIFS(Expenses!$J$4:$J$503,Expenses!$M$4:$M$503,10) -> 0 | G20: =SUMIFS(Income!$H$4:$H$503,Income!$O$4:$O$503,10) -> 0 | H20: =SUMIFS(Expenses!$I$4:$I$503,Expenses!$M$4:$M$503,10) -> 0 | I20: =G20-H20 -> 0 | J20: =IF(B20=0,0,D20/B20) -> 0
A21: =TEXT(EDATE(FY_START,10),"mmm yyyy") -> Nov 2026 | B21: =SUMIFS(Income!$F$4:$F$503,Income!$O$4:$O$503,11) -> 0 | C21: =SUMIFS(Expenses!$E$4:$E$503,Expenses!$M$4:$M$503,11) -> 0 | D21: =B21-C21 -> 0 | E21: =SUMIFS(Income!$L$4:$L$503,Income!$O$4:$O$503,11) -> 0 | F21: =SUMIFS(Expenses!$J$4:$J$503,Expenses!$M$4:$M$503,11) -> 0 | G21: =SUMIFS(Income!$H$4:$H$503,Income!$O$4:$O$503,11) -> 0 | H21: =SUMIFS(Expenses!$I$4:$I$503,Expenses!$M$4:$M$503,11) -> 0 | I21: =G21-H21 -> 0 | J21: =IF(B21=0,0,D21/B21) -> 0
A22: =TEXT(EDATE(FY_START,11),"mmm yyyy") -> Dec 2026 | B22: =SUMIFS(Income!$F$4:$F$503,Income!$O$4:$O$503,12) -> 0 | C22: =SUMIFS(Expenses!$E$4:$E$503,Expenses!$M$4:$M$503,12) -> 0 | D22: =B22-C22 -> 0 | E22: =SUMIFS(Income!$L$4:$L$503,Income!$O$4:$O$503,12) -> 0 | F22: =SUMIFS(Expenses!$J$4:$J$503,Expenses!$M$4:$M$503,12) -> 0 | G22: =SUMIFS(Income!$H$4:$H$503,Income!$O$4:$O$503,12) -> 0 | H22: =SUMIFS(Expenses!$I$4:$I$503,Expenses!$M$4:$M$503,12) -> 0 | I22: =G22-H22 -> 0 | J22: =IF(B22=0,0,D22/B22) -> 0
A23: TOTAL | B23: =SUM(B11:B22) -> 24500 | C23: =SUM(C11:C22) -> 11400 | D23: =SUM(D11:D22) -> 13100 | E23: =SUM(E11:E22) -> 20600 | F23: =SUM(F11:F22) -> 11595 | G23: =SUM(G11:G22) -> 825 | H23: =SUM(H11:H22) -> 195 | I23: =SUM(I11:I22) -> 630 | J23: =IF(B23=0,0,D23/B23) -> 0.53469388
A26: Income by category | B26: Revenue (excl. VAT) | C26: % of total | E26: Expenses by category | F26: Amount (excl. VAT) | G26: % of total
A27: =Settings!E4 -> Consulting / services | B27: =SUMIFS(Income!$F$4:$F$503,Income!$E$4:$E$503,A27,Income!$O$4:$O$503,">=1",Income!$O$4:$O$503,"<=12") -> 12000 | C27: =IF($B$23=0,0,B27/$B$23) -> 0.48979592 | E27: =Settings!F4 -> Software & subscriptions | F27: =SUMIFS(Expenses!$E$4:$E$503,Expenses!$D$4:$D$503,E27,Expenses!$M$4:$M$503,">=1",Expenses!$M$4:$M$503,"<=12") -> 2400 | G27: =IF($C$23=0,0,F27/$C$23) -> 0.21052632
A28: =Settings!E5 -> Freelance project | B28: =SUMIFS(Income!$F$4:$F$503,Income!$E$4:$E$503,A28,Income!$O$4:$O$503,">=1",Income!$O$4:$O$503,"<=12") -> 12500 | C28: =IF($B$23=0,0,B28/$B$23) -> 0.51020408 | E28: =Settings!F5 -> Office / coworking rent | F28: =SUMIFS(Expenses!$E$4:$E$503,Expenses!$D$4:$D$503,E28,Expenses!$M$4:$M$503,">=1",Expenses!$M$4:$M$503,"<=12") -> 1500 | G28: =IF($C$23=0,0,F28/$C$23) -> 0.13157895
A29: =Settings!E6 -> Retainer | B29: =SUMIFS(Income!$F$4:$F$503,Income!$E$4:$E$503,A29,Income!$O$4:$O$503,">=1",Income!$O$4:$O$503,"<=12") -> 0 | C29: =IF($B$23=0,0,B29/$B$23) -> 0 | E29: =Settings!F6 -> Trade licence & permits | F29: =SUMIFS(Expenses!$E$4:$E$503,Expenses!$D$4:$D$503,E29,Expenses!$M$4:$M$503,">=1",Expenses!$M$4:$M$503,"<=12") -> 7500 | G29: =IF($C$23=0,0,F29/$C$23) -> 0.65789474
A30: =Settings!E7 -> Product sales | B30: =SUMIFS(Income!$F$4:$F$503,Income!$E$4:$E$503,A30,Income!$O$4:$O$503,">=1",Income!$O$4:$O$503,"<=12") -> 0 | C30: =IF($B$23=0,0,B30/$B$23) -> 0 | E30: =Settings!F7 -> Marketing & advertising | F30: =SUMIFS(Expenses!$E$4:$E$503,Expenses!$D$4:$D$503,E30,Expenses!$M$4:$M$503,">=1",Expenses!$M$4:$M$503,"<=12") -> 0 | G30: =IF($C$23=0,0,F30/$C$23) -> 0
A31: =Settings!E8 -> Commission | B31: =SUMIFS(Income!$F$4:$F$503,Income!$E$4:$E$503,A31,Income!$O$4:$O$503,">=1",Income!$O$4:$O$503,"<=12") -> 0 | C31: =IF($B$23=0,0,B31/$B$23) -> 0 | E31: =Settings!F8 -> Travel & transport | F31: =SUMIFS(Expenses!$E$4:$E$503,Expenses!$D$4:$D$503,E31,Expenses!$M$4:$M$503,">=1",Expenses!$M$4:$M$503,"<=12") -> 0 | G31: =IF($C$23=0,0,F31/$C$23) -> 0
A32: =Settings!E9 -> Training | B32: =SUMIFS(Income!$F$4:$F$503,Income!$E$4:$E$503,A32,Income!$O$4:$O$503,">=1",Income!$O$4:$O$503,"<=12") -> 0 | C32: =IF($B$23=0,0,B32/$B$23) -> 0 | E32: =Settings!F9 -> Telecom & internet | F32: =SUMIFS(Expenses!$E$4:$E$503,Expenses!$D$4:$D$503,E32,Expenses!$M$4:$M$503,">=1",Expenses!$M$4:$M$503,"<=12") -> 0 | G32: =IF($C$23=0,0,F32/$C$23) -> 0
A33: =Settings!E10 -> Other income | B33: =SUMIFS(Income!$F$4:$F$503,Income!$E$4:$E$503,A33,Income!$O$4:$O$503,">=1",Income!$O$4:$O$503,"<=12") -> 0 | C33: =IF($B$23=0,0,B33/$B$23) -> 0 | E33: =Settings!F10 -> Professional fees (legal/accounting) | F33: =SUMIFS(Expenses!$E$4:$E$503,Expenses!$D$4:$D$503,E33,Expenses!$M$4:$M$503,">=1",Expenses!$M$4:$M$503,"<=12") -> 0 | G33: =IF($C$23=0,0,F33/$C$23) -> 0
E34: =Settings!F11 -> Bank & payment fees | F34: =SUMIFS(Expenses!$E$4:$E$503,Expenses!$D$4:$D$503,E34,Expenses!$M$4:$M$503,">=1",Expenses!$M$4:$M$503,"<=12") -> 0 | G34: =IF($C$23=0,0,F34/$C$23) -> 0
E35: =Settings!F12 -> Equipment & hardware | F35: =SUMIFS(Expenses!$E$4:$E$503,Expenses!$D$4:$D$503,E35,Expenses!$M$4:$M$503,">=1",Expenses!$M$4:$M$503,"<=12") -> 0 | G35: =IF($C$23=0,0,F35/$C$23) -> 0
E36: =Settings!F13 -> Contractors & salaries | F36: =SUMIFS(Expenses!$E$4:$E$503,Expenses!$D$4:$D$503,E36,Expenses!$M$4:$M$503,">=1",Expenses!$M$4:$M$503,"<=12") -> 0 | G36: =IF($C$23=0,0,F36/$C$23) -> 0
E37: =Settings!F14 -> Insurance | F37: =SUMIFS(Expenses!$E$4:$E$503,Expenses!$D$4:$D$503,E37,Expenses!$M$4:$M$503,">=1",Expenses!$M$4:$M$503,"<=12") -> 0 | G37: =IF($C$23=0,0,F37/$C$23) -> 0
E38: =Settings!F15 -> Meals & entertainment | F38: =SUMIFS(Expenses!$E$4:$E$503,Expenses!$D$4:$D$503,E38,Expenses!$M$4:$M$503,">=1",Expenses!$M$4:$M$503,"<=12") -> 0 | G38: =IF($C$23=0,0,F38/$C$23) -> 0
E39: =Settings!F16 -> Other expense | F39: =SUMIFS(Expenses!$E$4:$E$503,Expenses!$D$4:$D$503,E39,Expenses!$M$4:$M$503,">=1",Expenses!$M$4:$M$503,"<=12") -> 0 | G39: =IF($C$23=0,0,F39/$C$23) -> 0
A42: Receivables ageing (unpaid) | B42: Count | C42: Amount incl. VAT
A43: Not yet overdue | B43: =COUNTIFS(Income!$M$4:$M$503,">=0",Income!$M$4:$M$503,"<="&OVERDUE_DAYS) -> 0 | C43: =SUMIFS(Income!$I$4:$I$503,Income!$M$4:$M$503,">=0",Income!$M$4:$M$503,"<="&OVERDUE_DAYS) -> 0
A44: Overdue 1–30 days | B44: =COUNTIFS(Income!$M$4:$M$503,">"&OVERDUE_DAYS,Income!$M$4:$M$503,"<="&(OVERDUE_DAYS+30)) -> 0 | C44: =SUMIFS(Income!$I$4:$I$503,Income!$M$4:$M$503,">"&OVERDUE_DAYS,Income!$M$4:$M$503,"<="&(OVERDUE_DAYS+30)) -> 0
A45: Overdue 31–90 days | B45: =COUNTIFS(Income!$M$4:$M$503,">"&(OVERDUE_DAYS+30),Income!$M$4:$M$503,"<="&(OVERDUE_DAYS+90)) -> 0 | C45: =SUMIFS(Income!$I$4:$I$503,Income!$M$4:$M$503,">"&(OVERDUE_DAYS+30),Income!$M$4:$M$503,"<="&(OVERDUE_DAYS+90)) -> 0
A46: Overdue 90+ days | B46: =COUNTIFS(Income!$M$4:$M$503,">"&(OVERDUE_DAYS+90)) -> 1 | C46: =SUMIFS(Income!$I$4:$I$503,Income!$M$4:$M$503,">"&(OVERDUE_DAYS+90)) -> 4725

Sheet Settings
A1: Settings
A2: Edit the blue cells. Yellow = check these before use.
A3: Setting | B3: Value | C3: Notes / source | E3: Income categories | F3: Expense categories | G3: VAT treatment
A4: Business / trade name | B4: Your Business Name | C4: Appears on the Dashboard. | E4: Consulting / services | F4: Software & subscriptions | G4: Standard 5%
A5: Financial year start | B5: 46023 | C5: Dashboard months and Corporate Tax estimate run 12 months from this date. | E5: Freelance project | F5: Office / coworking rent | G5: Zero-rated 0%
A6: VAT registered? (Yes/No) | B6: Yes | C6: If No, VAT columns still calculate so you can see what you would charge once registered. | E6: Retainer | F6: Trade licence & permits | G6: Exempt
A7: Standard VAT rate | B7: 0.05 | C7: UAE standard rate. Source: Federal Decree-Law No. 8 of 2017, tax.gov.ae; checked 2026-09-17. | E7: Product sales | F7: Marketing & advertising | G7: Out of scope
A8: VAT mandatory registration threshold | B8: 375000 | C8: Taxable supplies in past 12 months (or expected in the next 30 days) - a rolling test, not a year-end one. Unchanged for 2026; checked 2026-09-17. | E8: Commission | F8: Travel & transport
A9: VAT voluntary registration threshold | B9: 187500 | C9: Optional registration is available from this level of supplies or taxable expenses. Unchanged for 2026; checked 2026-09-17. | E9: Training | F9: Telecom & internet | G9: Yes/No
A10: Corporate Tax rate | B10: 0.09 | C10: Source: Federal Decree-Law No. 47 of 2022; checked 2026-09-17. | E10: Other income | F10: Professional fees (legal/accounting) | G10: Yes
A11: Corporate Tax 0% band (taxable income) | B11: 375000 | C11: Taxable income up to this amount is taxed at 0%. Source: Federal Decree-Law No. 47 of 2022; checked 2026-09-17. | F11: Bank & payment fees | G11: No
A12: Elect Small Business Relief? (Yes/No) | B12: Yes | C12: Available if revenue ≤ threshold below, for tax periods ending on or before 31 Dec 2029 (extended by Ministerial Decision 131 of 2026). Election is made in the CT return, every period — it is not automatic. | F12: Equipment & hardware
A13: Small Business Relief revenue threshold | B13: 3000000 | C13: Revenue, not profit - the test is turnover. Source: Ministerial Decision 73 of 2023; checked 2026-09-17. | F13: Contractors & salaries | G13: Payment method
A14: Small Business Relief last eligible period end | B14: 47483 | C14: Relief not available for periods ending after this date. Extended from 31 Dec 2026 to 31 Dec 2029 by Ministerial Decision 131 of 2026; checked 2026-09-10. | F14: Insurance | G14: Bank transfer
A15: Current VAT return period — start | B15: 46023 | C15: Your FTA-assigned tax period (quarterly for most SMEs). Used by the VAT Return sheet. | F15: Meals & entertainment | G15: Card
A16: Current VAT return period — end | B16: 46112 | F16: Other expense | G16: Cash
A17: Opening cash balance | B17: 0 | C17: Bank + cash at financial-year start (for the cash position tile). | G17: PayPal / Stripe
A18: Invoice overdue after (days) | B18: 30 | C18: Used for the receivables ageing on the Dashboard. | E18: Payment status | G18: Cheque
E19: Paid | G19: Other
A20: Emirates ID / TRN (optional, for your records) | E20: Unpaid
A21: Tax Registration Number (TRN) | E21: Partially paid
E22: Written off

Sheet Income
A1: Income — invoices issued
A2: One row per invoice. Blue = type. VAT, totals and ageing are calculated.
A3: Invoice date | B3: Invoice # | C3: Client | D3: Description | E3: Category | F3: Amount excl. VAT (AED) | G3: VAT treatment | H3: VAT amount (AED) | I3: Total incl. VAT (AED) | J3: Payment status | K3: Date paid | L3: Amount received (AED) | M3: Days outstanding | N3: Overdue? | O3: Month # | P3: In VAT period?
A4: 46034 | B4: INV-001 | C4: Al Noor Trading LLC | D4: Brand strategy workshop | E4: Consulting / services | F4: 12000 | G4: Standard 5% | H4: =IF(F4="","",IF(G4="Standard 5%",F4*VAT_RATE,0)) -> 600 | I4: =IF(F4="","",F4+H4) -> 12600 | J4: Paid | K4: 46050 | L4: 12600 | M4: =IF(OR(A4="",J4="Paid",J4="Written off"),"",TODAY()-A4) | N4: =IF(M4="","",IF(M4>OVERDUE_DAYS,"OVERDUE","")) | O4: =IF(A4="","",IF(A4<FY_START,0,(YEAR(A4)-YEAR(FY_START))*12+MONTH(A4)-MONTH(FY_START)+1)) -> 1 | P4: =IF(A4="","",IF(AND(A4>=VP_START,A4<=VP_END),1,0)) -> 1
A5: 46056 | B5: INV-002 | C5: Sarah K. (Dubai) | D5: Website copywriting | E5: Freelance project | F5: 4500 | G5: Standard 5% | H5: =IF(F5="","",IF(G5="Standard 5%",F5*VAT_RATE,0)) -> 225 | I5: =IF(F5="","",F5+H5) -> 4725 | J5: Unpaid | M5: =IF(OR(A5="",J5="Paid",J5="Written off"),"",TODAY()-A5) -> 229 | N5: =IF(M5="","",IF(M5>OVERDUE_DAYS,"OVERDUE","")) -> OVERDUE | O5: =IF(A5="","",IF(A5<FY_START,0,(YEAR(A5)-YEAR(FY_START))*12+MONTH(A5)-MONTH(FY_START)+1)) -> 2 | P5: =IF(A5="","",IF(AND(A5>=VP_START,A5<=VP_END),1,0)) -> 1
A6: 46073 | B6: INV-003 | C6: Nordic Design AB (Sweden) | D6: Export of design services | E6: Freelance project | F6: 8000 | G6: Zero-rated 0% | H6: =IF(F6="","",IF(G6="Standard 5%",F6*VAT_RATE,0)) -> 0 | I6: =IF(F6="","",F6+H6) -> 8000 | J6: Paid | K6: 46086 | L6: 8000 | M6: =IF(OR(A6="",J6="Paid",J6="Written off"),"",TODAY()-A6) | N6: =IF(M6="","",IF(M6>OVERDUE_DAYS,"OVERDUE","")) | O6: =IF(A6="","",IF(A6<FY_START,0,(YEAR(A6)-YEAR(FY_START))*12+MONTH(A6)-MONTH(FY_START)+1)) -> 2 | P6: =IF(A6="","",IF(AND(A6>=VP_START,A6<=VP_END),1,0)) -> 1
H7: =IF(F7="","",IF(G7="Standard 5%",F7*VAT_RATE,0)) | I7: =IF(F7="","",F7+H7) | M7: =IF(OR(A7="",J7="Paid",J7="Written off"),"",TODAY()-A7) | N7: =IF(M7="","",IF(M7>OVERDUE_DAYS,"OVERDUE","")) | O7: =IF(A7="","",IF(A7<FY_START,0,(YEAR(A7)-YEAR(FY_START))*12+MONTH(A7)-MONTH(FY_START)+1)) | P7: =IF(A7="","",IF(AND(A7>=VP_START,A7<=VP_END),1,0))
H8: =IF(F8="","",IF(G8="Standard 5%",F8*VAT_RATE,0)) | I8: =IF(F8="","",F8+H8) | M8: =IF(OR(A8="",J8="Paid",J8="Written off"),"",TODAY()-A8) | N8: =IF(M8="","",IF(M8>OVERDUE_DAYS,"OVERDUE","")) | O8: =IF(A8="","",IF(A8<FY_START,0,(YEAR(A8)-YEAR(FY_START))*12+MONTH(A8)-MONTH(FY_START)+1)) | P8: =IF(A8="","",IF(AND(A8>=VP_START,A8<=VP_END),1,0))
H9: =IF(F9="","",IF(G9="Standard 5%",F9*VAT_RATE,0)) | I9: =IF(F9="","",F9+H9) | M9: =IF(OR(A9="",J9="Paid",J9="Written off"),"",TODAY()-A9) | N9: =IF(M9="","",IF(M9>OVERDUE_DAYS,"OVERDUE","")) | O9: =IF(A9="","",IF(A9<FY_START,0,(YEAR(A9)-YEAR(FY_START))*12+MONTH(A9)-MONTH(FY_START)+1)) | P9: =IF(A9="","",IF(AND(A9>=VP_START,A9<=VP_END),1,0))
H10: =IF(F10="","",IF(G10="Standard 5%",F10*VAT_RATE,0)) | I10: =IF(F10="","",F10+H10) | M10: =IF(OR(A10="",J10="Paid",J10="Written off"),"",TODAY()-A10) | N10: =IF(M10="","",IF(M10>OVERDUE_DAYS,"OVERDUE","")) | O10: =IF(A10="","",IF(A10<FY_START,0,(YEAR(A10)-YEAR(FY_START))*12+MONTH(A10)-MONTH(FY_START)+1)) | P10: =IF(A10="","",IF(AND(A10>=VP_START,A10<=VP_END),1,0))
H11: =IF(F11="","",IF(G11="Standard 5%",F11*VAT_RATE,0)) | I11: =IF(F11="","",F11+H11) | M11: =IF(OR(A11="",J11="Paid",J11="Written off"),"",TODAY()-A11) | N11: =IF(M11="","",IF(M11>OVERDUE_DAYS,"OVERDUE","")) | O11: =IF(A11="","",IF(A11<FY_START,0,(YEAR(A11)-YEAR(FY_START))*12+MONTH(A11)-MONTH(FY_START)+1)) | P11: =IF(A11="","",IF(AND(A11>=VP_START,A11<=VP_END),1,0))
H12: =IF(F12="","",IF(G12="Standard 5%",F12*VAT_RATE,0)) | I12: =IF(F12="","",F12+H12) | M12: =IF(OR(A12="",J12="Paid",J12="Written off"),"",TODAY()-A12) | N12: =IF(M12="","",IF(M12>OVERDUE_DAYS,"OVERDUE","")) | O12: =IF(A12="","",IF(A12<FY_START,0,(YEAR(A12)-YEAR(FY_START))*12+MONTH(A12)-MONTH(FY_START)+1)) | P12: =IF(A12="","",IF(AND(A12>=VP_START,A12<=VP_END),1,0))
H13: =IF(F13="","",IF(G13="Standard 5%",F13*VAT_RATE,0)) | I13: =IF(F13="","",F13+H13) | M13: =IF(OR(A13="",J13="Paid",J13="Written off"),"",TODAY()-A13) | N13: =IF(M13="","",IF(M13>OVERDUE_DAYS,"OVERDUE","")) | O13: =IF(A13="","",IF(A13<FY_START,0,(YEAR(A13)-YEAR(FY_START))*12+MONTH(A13)-MONTH(FY_START)+1)) | P13: =IF(A13="","",IF(AND(A13>=VP_START,A13<=VP_END),1,0))
H14: =IF(F14="","",IF(G14="Standard 5%",F14*VAT_RATE,0)) | I14: =IF(F14="","",F14+H14) | M14: =IF(OR(A14="",J14="Paid",J14="Written off"),"",TODAY()-A14) | N14: =IF(M14="","",IF(M14>OVERDUE_DAYS,"OVERDUE","")) | O14: =IF(A14="","",IF(A14<FY_START,0,(YEAR(A14)-YEAR(FY_START))*12+MONTH(A14)-MONTH(FY_START)+1)) | P14: =IF(A14="","",IF(AND(A14>=VP_START,A14<=VP_END),1,0))
H15: =IF(F15="","",IF(G15="Standard 5%",F15*VAT_RATE,0)) | I15: =IF(F15="","",F15+H15) | M15: =IF(OR(A15="",J15="Paid",J15="Written off"),"",TODAY()-A15) | N15: =IF(M15="","",IF(M15>OVERDUE_DAYS,"OVERDUE","")) | O15: =IF(A15="","",IF(A15<FY_START,0,(YEAR(A15)-YEAR(FY_START))*12+MONTH(A15)-MONTH(FY_START)+1)) | P15: =IF(A15="","",IF(AND(A15>=VP_START,A15<=VP_END),1,0))
H16: =IF(F16="","",IF(G16="Standard 5%",F16*VAT_RATE,0)) | I16: =IF(F16="","",F16+H16) | M16: =IF(OR(A16="",J16="Paid",J16="Written off"),"",TODAY()-A16) | N16: =IF(M16="","",IF(M16>OVERDUE_DAYS,"OVERDUE","")) | O16: =IF(A16="","",IF(A16<FY_START,0,(YEAR(A16)-YEAR(FY_START))*12+MONTH(A16)-MONTH(FY_START)+1)) | P16: =IF(A16="","",IF(AND(A16>=VP_START,A16<=VP_END),1,0))
H17: =IF(F17="","",IF(G17="Standard 5%",F17*VAT_RATE,0)) | I17: =IF(F17="","",F17+H17) | M17: =IF(OR(A17="",J17="Paid",J17="Written off"),"",TODAY()-A17) | N17: =IF(M17="","",IF(M17>OVERDUE_DAYS,"OVERDUE","")) | O17: =IF(A17="","",IF(A17<FY_START,0,(YEAR(A17)-YEAR(FY_START))*12+MONTH(A17)-MONTH(FY_START)+1)) | P17: =IF(A17="","",IF(AND(A17>=VP_START,A17<=VP_END),1,0))
H18: =IF(F18="","",IF(G18="Standard 5%",F18*VAT_RATE,0)) | I18: =IF(F18="","",F18+H18) | M18: =IF(OR(A18="",J18="Paid",J18="Written off"),"",TODAY()-A18) | N18: =IF(M18="","",IF(M18>OVERDUE_DAYS,"OVERDUE","")) | O18: =IF(A18="","",IF(A18<FY_START,0,(YEAR(A18)-YEAR(FY_START))*12+MONTH(A18)-MONTH(FY_START)+1)) | P18: =IF(A18="","",IF(AND(A18>=VP_START,A18<=VP_END),1,0))
... H503: =IF(F503="","",IF(G503="Standard 5%",F503*VAT_RATE,0)) | I503: =IF(F503="","",F503+H503) | M503: =IF(OR(A503="",J503="Paid",J503="Written off"),"",TODAY()-A503) | N503: =IF(M503="","",IF(M503>OVERDUE_DAYS,"OVERDUE","")) | O503: =IF(A503="","",IF(A503<FY_START,0,(YEAR(A503)-YEAR(FY_START))*12+MONTH(A503)-MONTH(FY_START)+1)) | P503: =IF(A503="","",IF(AND(A503>=VP_START,A503<=VP_END),1,0))

Sheet Expenses
A1: Expenses — business costs
A2: One row per receipt / bill. Only tick 'Yes' for recoverable input VAT if you hold a valid tax invoice.
A3: Date | B3: Supplier | C3: Description | D3: Category | E3: Amount excl. VAT (AED) | F3: VAT treatment | G3: VAT on invoice (AED) | H3: Input VAT recoverable? (Yes/No) | I3: Recoverable VAT (AED) | J3: Total paid (AED) | K3: Payment method | L3: Deductible for CT? (Yes/No) | M3: Month # | N3: In VAT period?
A4: 46027 | B4: Dubai Economy (DED) | C4: Freelance permit renewal | D4: Trade licence & permits | E4: 7500 | F4: Out of scope | G4: =IF(E4="","",IF(F4="Standard 5%",E4*VAT_RATE,0)) -> 0 | H4: No | I4: =IF(E4="","",IF(AND(H4="Yes",F4="Standard 5%"),G4,0)) -> 0 | J4: =IF(E4="","",E4+G4) -> 7500 | K4: Bank transfer | L4: Yes | M4: =IF(A4="","",IF(A4<FY_START,0,(YEAR(A4)-YEAR(FY_START))*12+MONTH(A4)-MONTH(FY_START)+1)) -> 1 | N4: =IF(A4="","",IF(AND(A4>=VP_START,A4<=VP_END),1,0)) -> 1
A5: 46037 | B5: Adobe | C5: Creative Cloud annual | D5: Software & subscriptions | E5: 2400 | F5: Standard 5% | G5: =IF(E5="","",IF(F5="Standard 5%",E5*VAT_RATE,0)) -> 120 | H5: Yes | I5: =IF(E5="","",IF(AND(H5="Yes",F5="Standard 5%"),G5,0)) -> 120 | J5: =IF(E5="","",E5+G5) -> 2520 | K5: Card | L5: Yes | M5: =IF(A5="","",IF(A5<FY_START,0,(YEAR(A5)-YEAR(FY_START))*12+MONTH(A5)-MONTH(FY_START)+1)) -> 1 | N5: =IF(A5="","",IF(AND(A5>=VP_START,A5<=VP_END),1,0)) -> 1
A6: 46061 | B6: Nasab Coworking | C6: Hot desk — February | D6: Office / coworking rent | E6: 1500 | F6: Standard 5% | G6: =IF(E6="","",IF(F6="Standard 5%",E6*VAT_RATE,0)) -> 75 | H6: Yes | I6: =IF(E6="","",IF(AND(H6="Yes",F6="Standard 5%"),G6,0)) -> 75 | J6: =IF(E6="","",E6+G6) -> 1575 | K6: Card | L6: Yes | M6: =IF(A6="","",IF(A6<FY_START,0,(YEAR(A6)-YEAR(FY_START))*12+MONTH(A6)-MONTH(FY_START)+1)) -> 2 | N6: =IF(A6="","",IF(AND(A6>=VP_START,A6<=VP_END),1,0)) -> 1
G7: =IF(E7="","",IF(F7="Standard 5%",E7*VAT_RATE,0)) | I7: =IF(E7="","",IF(AND(H7="Yes",F7="Standard 5%"),G7,0)) | J7: =IF(E7="","",E7+G7) | M7: =IF(A7="","",IF(A7<FY_START,0,(YEAR(A7)-YEAR(FY_START))*12+MONTH(A7)-MONTH(FY_START)+1)) | N7: =IF(A7="","",IF(AND(A7>=VP_START,A7<=VP_END),1,0))
G8: =IF(E8="","",IF(F8="Standard 5%",E8*VAT_RATE,0)) | I8: =IF(E8="","",IF(AND(H8="Yes",F8="Standard 5%"),G8,0)) | J8: =IF(E8="","",E8+G8) | M8: =IF(A8="","",IF(A8<FY_START,0,(YEAR(A8)-YEAR(FY_START))*12+MONTH(A8)-MONTH(FY_START)+1)) | N8: =IF(A8="","",IF(AND(A8>=VP_START,A8<=VP_END),1,0))
G9: =IF(E9="","",IF(F9="Standard 5%",E9*VAT_RATE,0)) | I9: =IF(E9="","",IF(AND(H9="Yes",F9="Standard 5%"),G9,0)) | J9: =IF(E9="","",E9+G9) | M9: =IF(A9="","",IF(A9<FY_START,0,(YEAR(A9)-YEAR(FY_START))*12+MONTH(A9)-MONTH(FY_START)+1)) | N9: =IF(A9="","",IF(AND(A9>=VP_START,A9<=VP_END),1,0))
G10: =IF(E10="","",IF(F10="Standard 5%",E10*VAT_RATE,0)) | I10: =IF(E10="","",IF(AND(H10="Yes",F10="Standard 5%"),G10,0)) | J10: =IF(E10="","",E10+G10) | M10: =IF(A10="","",IF(A10<FY_START,0,(YEAR(A10)-YEAR(FY_START))*12+MONTH(A10)-MONTH(FY_START)+1)) | N10: =IF(A10="","",IF(AND(A10>=VP_START,A10<=VP_END),1,0))
G11: =IF(E11="","",IF(F11="Standard 5%",E11*VAT_RATE,0)) | I11: =IF(E11="","",IF(AND(H11="Yes",F11="Standard 5%"),G11,0)) | J11: =IF(E11="","",E11+G11) | M11: =IF(A11="","",IF(A11<FY_START,0,(YEAR(A11)-YEAR(FY_START))*12+MONTH(A11)-MONTH(FY_START)+1)) | N11: =IF(A11="","",IF(AND(A11>=VP_START,A11<=VP_END),1,0))
G12: =IF(E12="","",IF(F12="Standard 5%",E12*VAT_RATE,0)) | I12: =IF(E12="","",IF(AND(H12="Yes",F12="Standard 5%"),G12,0)) | J12: =IF(E12="","",E12+G12) | M12: =IF(A12="","",IF(A12<FY_START,0,(YEAR(A12)-YEAR(FY_START))*12+MONTH(A12)-MONTH(FY_START)+1)) | N12: =IF(A12="","",IF(AND(A12>=VP_START,A12<=VP_END),1,0))
G13: =IF(E13="","",IF(F13="Standard 5%",E13*VAT_RATE,0)) | I13: =IF(E13="","",IF(AND(H13="Yes",F13="Standard 5%"),G13,0)) | J13: =IF(E13="","",E13+G13) | M13: =IF(A13="","",IF(A13<FY_START,0,(YEAR(A13)-YEAR(FY_START))*12+MONTH(A13)-MONTH(FY_START)+1)) | N13: =IF(A13="","",IF(AND(A13>=VP_START,A13<=VP_END),1,0))
G14: =IF(E14="","",IF(F14="Standard 5%",E14*VAT_RATE,0)) | I14: =IF(E14="","",IF(AND(H14="Yes",F14="Standard 5%"),G14,0)) | J14: =IF(E14="","",E14+G14) | M14: =IF(A14="","",IF(A14<FY_START,0,(YEAR(A14)-YEAR(FY_START))*12+MONTH(A14)-MONTH(FY_START)+1)) | N14: =IF(A14="","",IF(AND(A14>=VP_START,A14<=VP_END),1,0))
G15: =IF(E15="","",IF(F15="Standard 5%",E15*VAT_RATE,0)) | I15: =IF(E15="","",IF(AND(H15="Yes",F15="Standard 5%"),G15,0)) | J15: =IF(E15="","",E15+G15) | M15: =IF(A15="","",IF(A15<FY_START,0,(YEAR(A15)-YEAR(FY_START))*12+MONTH(A15)-MONTH(FY_START)+1)) | N15: =IF(A15="","",IF(AND(A15>=VP_START,A15<=VP_END),1,0))
G16: =IF(E16="","",IF(F16="Standard 5%",E16*VAT_RATE,0)) | I16: =IF(E16="","",IF(AND(H16="Yes",F16="Standard 5%"),G16,0)) | J16: =IF(E16="","",E16+G16) | M16: =IF(A16="","",IF(A16<FY_START,0,(YEAR(A16)-YEAR(FY_START))*12+MONTH(A16)-MONTH(FY_START)+1)) | N16: =IF(A16="","",IF(AND(A16>=VP_START,A16<=VP_END),1,0))
G17: =IF(E17="","",IF(F17="Standard 5%",E17*VAT_RATE,0)) | I17: =IF(E17="","",IF(AND(H17="Yes",F17="Standard 5%"),G17,0)) | J17: =IF(E17="","",E17+G17) | M17: =IF(A17="","",IF(A17<FY_START,0,(YEAR(A17)-YEAR(FY_START))*12+MONTH(A17)-MONTH(FY_START)+1)) | N17: =IF(A17="","",IF(AND(A17>=VP_START,A17<=VP_END),1,0))
G18: =IF(E18="","",IF(F18="Standard 5%",E18*VAT_RATE,0)) | I18: =IF(E18="","",IF(AND(H18="Yes",F18="Standard 5%"),G18,0)) | J18: =IF(E18="","",E18+G18) | M18: =IF(A18="","",IF(A18<FY_START,0,(YEAR(A18)-YEAR(FY_START))*12+MONTH(A18)-MONTH(FY_START)+1)) | N18: =IF(A18="","",IF(AND(A18>=VP_START,A18<=VP_END),1,0))
... G503: =IF(E503="","",IF(F503="Standard 5%",E503*VAT_RATE,0)) | I503: =IF(E503="","",IF(AND(H503="Yes",F503="Standard 5%"),G503,0)) | J503: =IF(E503="","",E503+G503) | M503: =IF(A503="","",IF(A503<FY_START,0,(YEAR(A503)-YEAR(FY_START))*12+MONTH(A503)-MONTH(FY_START)+1)) | N503: =IF(A503="","",IF(AND(A503>=VP_START,A503<=VP_END),1,0))

Sheet VAT Return
A1: VAT Return helper
A2: Set the period in Settings (B15:B16). Copy these boxes into the FTA EmaraTax return.
B4: Period start | C4: =VP_START -> 46023
B5: Period end | C5: =VP_END -> 46112
B6: VAT registered? | C6: =Settings!B6 -> Yes
A8: Box | B8: Description | C8: Amount (AED) | D8: VAT (AED) | E8: How it is calculated
A9: 1a | B9: Standard-rated supplies (sales at 5%) | C9: =SUMIFS(Income!$F$4:$F$503,Income!$G$4:$G$503,"Standard 5%",Income!$P$4:$P$503,1) -> 16500 | D9: =SUMIFS(Income!$H$4:$H$503,Income!$G$4:$G$503,"Standard 5%",Income!$P$4:$P$503,1) -> 825 | E9: Income rows dated within the period with VAT treatment 'Standard 5%'.
A10: 4 | B10: Zero-rated supplies (exports, certain services) | C10: =SUMIFS(Income!$F$4:$F$503,Income!$G$4:$G$503,"Zero-rated 0%",Income!$P$4:$P$503,1) -> 8000 | D10: =0 -> 0 | E10: Income rows with 'Zero-rated 0%'.
A11: 5 | B11: Exempt supplies | C11: =SUMIFS(Income!$F$4:$F$503,Income!$G$4:$G$503,"Exempt",Income!$P$4:$P$503,1) -> 0 | D11: =0 -> 0 | E11: Income rows with 'Exempt'.
A12: — | B12: Out-of-scope income (not reported on the return) | C12: =SUMIFS(Income!$F$4:$F$503,Income!$G$4:$G$503,"Out of scope",Income!$P$4:$P$503,1) -> 0 | D12: =0 -> 0 | E12: Shown for reconciliation only.
A13: 8 | B13: TOTAL OUTPUT VAT DUE | C13: =C9+C10+C11 -> 24500 | D13: =D9+D10+D11 -> 825 | E13: Sum of boxes 1a, 4, 5.
A14: 9 | B14: Standard-rated expenses with recoverable input VAT | C14: =SUMIFS(Expenses!$E$4:$E$503,Expenses!$H$4:$H$503,"Yes",Expenses!$F$4:$F$503,"Standard 5%",Expenses!$N$4:$N$503,1) -> 3900 | D14: =SUMIFS(Expenses!$I$4:$I$503,Expenses!$N$4:$N$503,1) -> 195 | E14: Expense rows in the period where 'Input VAT recoverable' = Yes and treatment = Standard 5%.
A15: 11 | B15: TOTAL RECOVERABLE INPUT VAT | C15: =C14 -> 3900 | D15: =D14 -> 195
A16: 12/13 | B16: NET VAT PAYABLE (positive) / REFUNDABLE (negative) | D16: =D13-D15 -> 630 | E16: Output VAT − recoverable input VAT.
B17: CHECK — income in period not counted in any box above (must be 0) | D17: =SUMIFS(Income!$F$4:$F$503,Income!$P$4:$P$503,1)-C9-C10-C11-C12 -> 0
B18: Non-recoverable VAT paid in period (cost to you) | D18: =SUMIFS(Expenses!$G$4:$G$503,Expenses!$N$4:$N$503,1)-D14 -> 0
B19: CHECK — expenses in period with an unrecognised VAT treatment (must be 0) | D19: =SUMIFS(Expenses!$E$4:$E$503,Expenses!$N$4:$N$503,1)-SUMIFS(Expenses!$E$4:$E$503,Expenses!$F$4:$F$503,"Standard 5%",Expenses!$N$4:$N$503,1)-SUMIFS(Expenses!$E$4:$E$503,Expenses!$F$4:$F$503,"Zero-rated 0%",Expenses!$N$4:$N$503,1)-SUMIFS(Expenses!$E$4:$E$503,Expenses!$F$4:$F$503,"Exempt",Expenses!$N$4:$N$503,1)-SUMIFS(Expenses!$E$4:$E$503,Expenses!$F$4:$F$503,"Out of scope",Expenses!$N$4:$N$503,1) -> 0
B20: Registration check — taxable turnover, last 12 months to today | D20: =SUMIFS(Income!$F$4:$F$503,Income!$G$4:$G$503,"Standard 5%",Income!$A$4:$A$503,">"&(TODAY()-365))+SUMIFS(Income!$F$4:$F$503,Income!$G$4:$G$503,"Zero-rated 0%",Income!$A$4:$A$503,">"&(TODAY()-365)) -> 24500
B21: Status vs thresholds | D21: =IF(D20>=VAT_MAND,"ABOVE MANDATORY THRESHOLD — must be registered",IF(D20>=VAT_VOL,"Above voluntary threshold — may register","Below voluntary threshold")) -> Below voluntary threshold
B23: Note: taxable turnover = standard-rated + zero-rated supplies (exempt and out-of-scope excluded). Always confirm box mapping against the current FTA return form.

Sheet Corporate Tax
A1: Corporate Tax estimate — current financial year
A2: Accrual basis: all invoices issued and costs incurred in the 12 months from the financial-year start.
A3: Line | B3: AED | C3: Notes
A4: Financial year | B4: =TEXT(FY_START,"dd-mmm-yyyy")&" to "&TEXT(EDATE(FY_START,12)-1,"dd-mmm-yyyy") -> 01-Jan-2026 to 31-Dec-2026 | C4: From Settings.
A5: Revenue (all income excl. VAT) | B5: =SUMIFS(Income!$F$4:$F$503,Income!$A$4:$A$503,">="&FY_START,Income!$A$4:$A$503,"<="&EDATE(FY_START,12)-1) -> 24500 | C5: All Income rows in the year, regardless of payment status (accrual).
A6: Deductible expenses (excl. VAT, marked deductible = Yes) | B6: =SUMIFS(Expenses!$E$4:$E$503,Expenses!$L$4:$L$503,"Yes",Expenses!$A$4:$A$503,">="&FY_START,Expenses!$A$4:$A$503,"<="&EDATE(FY_START,12)-1) -> 11400 | C6: Note: entertainment is only 50% deductible under UAE CT law — adjust below if relevant.
A7: Non-recoverable VAT on deductible expenses | B7: =SUMIFS(Expenses!$G$4:$G$503,Expenses!$L$4:$L$503,"Yes",Expenses!$H$4:$H$503,"No",Expenses!$A$4:$A$503,">="&FY_START,Expenses!$A$4:$A$503,"<="&EDATE(FY_START,12)-1) -> 0 | C7: Irrecoverable VAT is a business cost.
A8: Manual adjustments (+ adds to income / − deducts) | B8: 0 | C8: Blue input: e.g. −50% of meals & entertainment, depreciation, disallowed fines.
A9: Accounting / taxable profit (estimate) | B9: =B5-B6-B7+B8 -> 13100 | C9: Revenue − expenses − irrecoverable VAT + adjustments.
A10: Small Business Relief elected? | B10: =SBR_ELECT -> Yes | C10: From Settings.
A11: Eligible for Small Business Relief this year? | B11: =IF(AND(SBR_ELECT="Yes",B5<=SBR_LIMIT,EDATE(FY_START,12)-1<=SBR_END),"Yes","No") -> Yes | C11: Requires revenue ≤ threshold AND period ending on/before the relief end date.
A12: Taxable income above 0% band | B12: =MAX(0,B9-CT_BAND) -> 0 | C12: Profit above the AED 375,000 band.
A13: ESTIMATED CORPORATE TAX | B13: =IF(B11="Yes",0,B12*CT_RATE) -> 0 | C13: 0 if relief applies; otherwise 9% × income above the band.
A14: Effective tax rate on profit | B14: =IF(B9<=0,0,B13/B9) -> 0
A15: Suggested monthly set-aside for CT | B15: =B13/12 -> 0 | C15: Park this each month so the payment is painless.
A18: Reminder: every taxable person (including freelancers with a licence/permit) must register for Corporate Tax with the FTA and file a return within 9 months of the financial-year end, even when the tax due is zero or Small Business Relief is claimed. Registration deadlines and penalties are not modelled here.
