Workbook

Sheet START HERE
A1: Reseller profit-after-fees calculator 2026
A2: Free. eBay · Poshmark · Mercari · Depop · Facebook Marketplace
A4: WHAT THIS DOES
A5: One item, every platform | B5: Type an item's cost, price and shipping into the Calculator sheet once. It shows the fee, what you receive, your profit and your ROI on every marketplace at the same time, and names the one that pays most. A row turns red when you would lose money.
A6: 20 at a time | B6: The 'Batch (20 items)' sheet does the same maths one row per item, with a dropdown to pick the marketplace per row.
A8: BEFORE YOU TRUST A NUMBER
A9: Check the rates | B9: Marketplaces change fees without much notice, and a stale rate quietly distorts every figure here. The Fees sheet carries a 'Rates last checked' date per row. eBay, Poshmark and Mercari were verified on 10 September 2026. Depop and Facebook Marketplace say 'not re-verified' in red — that is the honest state of those two rows. Five minutes on each platform's fee page and you can fix them yourself; everything recalculates.
A10: Buyer-paid shipping | B10: Only enter shipping that actually lands in your payout. On Poshmark the buyer pays the label directly, so leave it at 0. On eBay it usually does reach you — and eBay charges its percentage on it, which this sheet accounts for.
A11: Not modelled | B11: Promoted listings, store subscriptions, international and advertising fees, and sales tax. Add anything like that to 'Other costs'.
A13: HOW TO OPEN IT
A14: Excel | B14: Excel 2016 or newer. No macros, nothing to enable.
A15: Google Sheets | B15: File → Import → Upload, then 'Replace spreadsheet'. Everything works.
A17: IF THIS IS USEFUL
A18: Rate it | B18: A rating on the Gumroad page is the single most useful thing you can give back — it is what lets anyone else find this. It costs you ten seconds.
A19: The full tracker | B19: This prices one item. The Reseller Inventory & Profit Tracker 2026 runs the business: 500 inventory items with auto-generated SKUs, fees and ROI on every sale as you type, a death pile report for stale listings with suggested markdowns, dashboards for sell-through and best platform, and a Schedule-C-style tax summary at year end. $19, one file, no subscription. https://gum.co/u/ysjnz0ld
A21: DISCLAIMER
A22: Not tax or financial advice | B22: Fee rates are user-editable approximations. Verify them for your own account and region before making pricing decisions.

Sheet Calculator
A1: Reseller profit-after-fees calculator 2026
A2: Type your item into the blue cells once. Every marketplace is priced below, side by side.
A4: What you paid for the item | B4: 12 | C4: Your cost of goods — the thrift/wholesale price.
A5: Sale price you plan to list at | B5: 45 | C5: The item price the buyer pays, before shipping.
A6: Buyer-paid shipping YOU receive | B6: 0 | C6: 0 if you offer free shipping, or if the marketplace collects it and buys the label (Poshmark). Put the amount here only when it lands in your payout (typical on eBay).
A7: Your shipping cost (label + packaging) | B7: 6.5 | C7: What the label and box/poly-mailer actually cost you. Enter it even when shipping is free to the buyer — it comes out of your pocket either way.
A8: Other costs on this item | B8: 0.5 | C8: Cleaning, repair, gas share, supplies.
A10: What each marketplace leaves you
A11: Marketplace | B11: Fee | C11: Fee as % of what the buyer pays | D11: You receive | E11: Your total outlay | F11: PROFIT | G11: ROI | H11: Rates last checked
A12: =Fees!$A$4 -> eBay | B12: =MAX(IF(AND(Fees!$H$4>0,$B$5<Fees!$H$4),Fees!$I$4,($B$5+IF(Fees!$G$4="Y",$B$6,0))*Fees!$B$4+IF(AND(Fees!$E$4>0,$B$5<=Fees!$E$4),Fees!$D$4,Fees!$C$4)+($B$5+IF(Fees!$G$4="Y",$B$6,0))*Fees!$F$4),Fees!$J$4) -> 6.52 | C12: =IF(($B$5+$B$6)<=0,"-",B12/($B$5+$B$6)) -> 0.14488889 | D12: =$B$5+$B$6-B12 -> 38.48 | E12: =($B$4+$B$7+$B$8) -> 19 | F12: =D12-E12 -> 19.48 | G12: =IF(($B$4+$B$7+$B$8)<=0,"-",F12/($B$4+$B$7+$B$8)) -> 1.0252632 | H12: =Fees!$K$4 -> 2026-09-10
A13: =Fees!$A$5 -> Poshmark | B13: =MAX(IF(AND(Fees!$H$5>0,$B$5<Fees!$H$5),Fees!$I$5,($B$5+IF(Fees!$G$5="Y",$B$6,0))*Fees!$B$5+IF(AND(Fees!$E$5>0,$B$5<=Fees!$E$5),Fees!$D$5,Fees!$C$5)+($B$5+IF(Fees!$G$5="Y",$B$6,0))*Fees!$F$5),Fees!$J$5) -> 9 | C13: =IF(($B$5+$B$6)<=0,"-",B13/($B$5+$B$6)) -> 0.2 | D13: =$B$5+$B$6-B13 -> 36 | E13: =($B$4+$B$7+$B$8) -> 19 | F13: =D13-E13 -> 17 | G13: =IF(($B$4+$B$7+$B$8)<=0,"-",F13/($B$4+$B$7+$B$8)) -> 0.89473684 | H13: =Fees!$K$5 -> 2026-09-10
A14: =Fees!$A$6 -> Mercari | B14: =MAX(IF(AND(Fees!$H$6>0,$B$5<Fees!$H$6),Fees!$I$6,($B$5+IF(Fees!$G$6="Y",$B$6,0))*Fees!$B$6+IF(AND(Fees!$E$6>0,$B$5<=Fees!$E$6),Fees!$D$6,Fees!$C$6)+($B$5+IF(Fees!$G$6="Y",$B$6,0))*Fees!$F$6),Fees!$J$6) -> 4.5 | C14: =IF(($B$5+$B$6)<=0,"-",B14/($B$5+$B$6)) -> 0.1 | D14: =$B$5+$B$6-B14 -> 40.5 | E14: =($B$4+$B$7+$B$8) -> 19 | F14: =D14-E14 -> 21.5 | G14: =IF(($B$4+$B$7+$B$8)<=0,"-",F14/($B$4+$B$7+$B$8)) -> 1.1315789 | H14: =Fees!$K$6 -> 2026-09-16
A15: =Fees!$A$7 -> Depop | B15: =MAX(IF(AND(Fees!$H$7>0,$B$5<Fees!$H$7),Fees!$I$7,($B$5+IF(Fees!$G$7="Y",$B$6,0))*Fees!$B$7+IF(AND(Fees!$E$7>0,$B$5<=Fees!$E$7),Fees!$D$7,Fees!$C$7)+($B$5+IF(Fees!$G$7="Y",$B$6,0))*Fees!$F$7),Fees!$J$7) -> 1.935 | C15: =IF(($B$5+$B$6)<=0,"-",B15/($B$5+$B$6)) -> 0.043 | D15: =$B$5+$B$6-B15 -> 43.065 | E15: =($B$4+$B$7+$B$8) -> 19 | F15: =D15-E15 -> 24.065 | G15: =IF(($B$4+$B$7+$B$8)<=0,"-",F15/($B$4+$B$7+$B$8)) -> 1.2665789 | H15: =Fees!$K$7 -> 2026-09-11
A16: =Fees!$A$8 -> Facebook Marketplace | B16: =MAX(IF(AND(Fees!$H$8>0,$B$5<Fees!$H$8),Fees!$I$8,($B$5+IF(Fees!$G$8="Y",$B$6,0))*Fees!$B$8+IF(AND(Fees!$E$8>0,$B$5<=Fees!$E$8),Fees!$D$8,Fees!$C$8)+($B$5+IF(Fees!$G$8="Y",$B$6,0))*Fees!$F$8),Fees!$J$8) -> 4.5 | C16: =IF(($B$5+$B$6)<=0,"-",B16/($B$5+$B$6)) -> 0.1 | D16: =$B$5+$B$6-B16 -> 40.5 | E16: =($B$4+$B$7+$B$8) -> 19 | F16: =D16-E16 -> 21.5 | G16: =IF(($B$4+$B$7+$B$8)<=0,"-",F16/($B$4+$B$7+$B$8)) -> 1.1315789 | H16: =Fees!$K$8 -> 2026-09-11
A17: =Fees!$A$9 -> Other / edit me | B17: =MAX(IF(AND(Fees!$H$9>0,$B$5<Fees!$H$9),Fees!$I$9,($B$5+IF(Fees!$G$9="Y",$B$6,0))*Fees!$B$9+IF(AND(Fees!$E$9>0,$B$5<=Fees!$E$9),Fees!$D$9,Fees!$C$9)+($B$5+IF(Fees!$G$9="Y",$B$6,0))*Fees!$F$9),Fees!$J$9) -> 4.5 | C17: =IF(($B$5+$B$6)<=0,"-",B17/($B$5+$B$6)) -> 0.1 | D17: =$B$5+$B$6-B17 -> 40.5 | E17: =($B$4+$B$7+$B$8) -> 19 | F17: =D17-E17 -> 21.5 | G17: =IF(($B$4+$B$7+$B$8)<=0,"-",F17/($B$4+$B$7+$B$8)) -> 1.1315789 | H17: =Fees!$K$9 -> n/a
A19: Best marketplace for this item | B19: =INDEX(A12:A17,MATCH(MAX(F12:F17),F12:F17,0)) -> Depop
A20: Profit there | B20: =MAX(F12:F17) -> 24.065
A21: Worst on this list costs you | B21: =MAX(F12:F17)-MIN(F12:F17) -> 7.065 | C21: …more than the best one, on this single item. That is the whole point of checking before you list.
A23: Promoted listings, store subscriptions, international/ad fees and sales tax are not modelled. Rates marked 'not re-verified' are approximations — open the Fees sheet and check them against the marketplace's own fee page.
A25: Tracking a whole business, not one item?
A26: This sheet prices one item at a time. The full Reseller Inventory & Profit Tracker 2026 does the rest of the job: 500 items of inventory with auto SKUs, every sale's fees and ROI calculated as you type, a death-pile report for anything that has sat too long, sell-through and best-platform dashboards, and a Schedule-C-style tax summary at year end. $19, one file, no subscription — https://gum.co/u/ysjnz0ld

Sheet Fees
A1: Marketplace fee rates
A2: Blue cells are yours to edit. Every calculation on the Calculator sheet reads from here.
A3: Marketplace | B3: Fee % | C3: Per-order fee $ | D3: Per-order fee $ (small orders) | E3: Small order up to $ | F3: Processing % | G3: Fee charged on buyer-paid shipping? (Y/N) | H3: Flat fee applies under $ | I3: Flat fee $ | J3: Minimum fee $ | K3: Rates last checked | L3: Notes — check against the marketplace's own fee page
A4: eBay | B4: 0.136 | C4: 0.4 | D4: 0.3 | E4: 10 | F4: 0 | G4: Y | H4: 0 | I4: 0 | J4: 0 | K4: 2026-09-10 | L4: Final value fee 13.6% of the total (item + buyer-paid shipping + handling) plus $0.40 per order, or $0.30 on orders of $10 or less. Most categories; books/media and some others differ.
A5: Poshmark | B5: 0.2 | C5: 0 | D5: 0 | E5: 0 | F5: 0 | G5: N | H5: 15 | I5: 2.95 | J5: 0 | K5: 2026-09-10 | L5: Flat $2.95 on sales under $15, otherwise 20% of the sale price. No separate processing fee. The buyer pays shipping directly, so leave 'buyer-paid shipping you receive' at 0.
A6: Mercari | B6: 0.1 | C6: 0 | D6: 0 | E6: 0 | F6: 0 | G6: Y | H6: 0 | I6: 0 | J6: 0 | K6: 2026-09-16 | L6: Flat 10% on item + buyer-paid shipping. The old 2.9% + $0.50 seller processing fee was removed on 6 Jan 2025; buyers now pay a 3.6% Buyer Protection fee instead. NOT in this row: Mercari charges $2.00 to send a standard direct-deposit payout ($3.00 for Instant Pay). That is per payout, not per sale, so it is not a per-item fee - if you cash out once a month it is $2 across every sale that month, and if you cash out per sale it is $2 on each. Nowhere else in this sheet charges you to be paid.
A7: Depop | B7: 0 | C7: 0.45 | D7: 0.45 | E7: 0 | F7: 0.033 | G7: Y | H7: 0 | I7: 0 | J7: 0 | K7: 2026-09-11 | L7: No US selling commission since 2024 - it moved to the buyer. What remains on the seller is 3.3% + $0.45 payment processing, charged on item + shipping + tax. An optional Boosted Listing costs 12% on top if you use one; this row does not include it.
A8: Facebook Marketplace | B8: 0.1 | C8: 0 | D8: 0 | E8: 0 | F8: 0 | G8: Y | H8: 0 | I8: 0 | J8: 0.8 | K8: 2026-09-11 | L8: 10% of the buyer's total (item + the shipping you charge + the sales tax Meta collects), minimum $0.80 per order. Raised from 5% / $0.40 on 15 April 2024. Local pickup sales have no selling fee at all - price those with the 'Other' row set to 0%.
A9: Other / edit me | B9: 0.1 | C9: 0 | D9: 0 | E9: 0 | F9: 0 | G9: Y | H9: 0 | I9: 0 | J9: 0 | K9: n/a | L9: Blank slot — put any other marketplace's rates here.

Sheet Batch (20 items)
A1: Price 20 items at once
A2: Pick a marketplace per row. Same maths as the Calculator sheet, one row per item.
A3: Item | B3: Marketplace | C3: Item cost $ | D3: Sale price $ | E3: Buyer-paid shipping you receive $ | F3: Your shipping cost $ | G3: Other costs $ | H3: Fee | I3: You receive | J3: PROFIT | K3: ROI
A4: Example: Patagonia fleece | B4: eBay | C4: 12 | D4: 45 | E4: 0 | F4: 6.5 | G4: 0.5 | H4: =IF($B4="","",MAX(IF(AND(INDEX(Fees!$H$4:$H$9,MATCH($B4,Fees!$A$4:$A$9,0))>0,$D4<INDEX(Fees!$H$4:$H$9,MATCH($B4,Fees!$A$4:$A$9,0))),INDEX(Fees!$I$4:$I$9,MATCH($B4,Fees!$A$4:$A$9,0)),($D4+IF(INDEX(Fees!$G$4:$G$9,MATCH($B4,Fees!$A$4:$A$9,0))="Y",$E4,0))*INDEX(Fees!$B$4:$B$9,MATCH($B4,Fees!$A$4:$A$9,0))+IF(AND(INDEX(Fees!$E$4:$E$9,MATCH($B4,Fees!$A$4:$A$9,0))>0,$D4<=INDEX(Fees!$E$4:$E$9,MATCH($B4,Fees!$A$4:$A$9,0))),INDEX(Fees!$D$4:$D$9,MATCH($B4,Fees!$A$4:$A$9,0)),INDEX(Fees!$C$4:$C$9,MATCH($B4,Fees!$A$4:$A$9,0)))+($D4+IF(INDEX(Fees!$G$4:$G$9,MATCH($B4,Fees!$A$4:$A$9,0))="Y",$E4,0))*INDEX(Fees!$F$4:$F$9,MATCH($B4,Fees!$A$4:$A$9,0))),INDEX(Fees!$J$4:$J$9,MATCH($B4,Fees!$A$4:$A$9,0)))) -> 6.52 | I4: =IF($B4="","",$D4+$E4-$H4) -> 38.48 | J4: =IF($B4="","",$I4-($C4+$F4+$G4)) -> 19.48 | K4: =IF(OR($B4="",($C4+$F4+$G4)<=0),"",$J4/($C4+$F4+$G4)) -> 1.0252632
H5: =IF($B5="","",MAX(IF(AND(INDEX(Fees!$H$4:$H$9,MATCH($B5,Fees!$A$4:$A$9,0))>0,$D5<INDEX(Fees!$H$4:$H$9,MATCH($B5,Fees!$A$4:$A$9,0))),INDEX(Fees!$I$4:$I$9,MATCH($B5,Fees!$A$4:$A$9,0)),($D5+IF(INDEX(Fees!$G$4:$G$9,MATCH($B5,Fees!$A$4:$A$9,0))="Y",$E5,0))*INDEX(Fees!$B$4:$B$9,MATCH($B5,Fees!$A$4:$A$9,0))+IF(AND(INDEX(Fees!$E$4:$E$9,MATCH($B5,Fees!$A$4:$A$9,0))>0,$D5<=INDEX(Fees!$E$4:$E$9,MATCH($B5,Fees!$A$4:$A$9,0))),INDEX(Fees!$D$4:$D$9,MATCH($B5,Fees!$A$4:$A$9,0)),INDEX(Fees!$C$4:$C$9,MATCH($B5,Fees!$A$4:$A$9,0)))+($D5+IF(INDEX(Fees!$G$4:$G$9,MATCH($B5,Fees!$A$4:$A$9,0))="Y",$E5,0))*INDEX(Fees!$F$4:$F$9,MATCH($B5,Fees!$A$4:$A$9,0))),INDEX(Fees!$J$4:$J$9,MATCH($B5,Fees!$A$4:$A$9,0)))) | I5: =IF($B5="","",$D5+$E5-$H5) | J5: =IF($B5="","",$I5-($C5+$F5+$G5)) | K5: =IF(OR($B5="",($C5+$F5+$G5)<=0),"",$J5/($C5+$F5+$G5))
H6: =IF($B6="","",MAX(IF(AND(INDEX(Fees!$H$4:$H$9,MATCH($B6,Fees!$A$4:$A$9,0))>0,$D6<INDEX(Fees!$H$4:$H$9,MATCH($B6,Fees!$A$4:$A$9,0))),INDEX(Fees!$I$4:$I$9,MATCH($B6,Fees!$A$4:$A$9,0)),($D6+IF(INDEX(Fees!$G$4:$G$9,MATCH($B6,Fees!$A$4:$A$9,0))="Y",$E6,0))*INDEX(Fees!$B$4:$B$9,MATCH($B6,Fees!$A$4:$A$9,0))+IF(AND(INDEX(Fees!$E$4:$E$9,MATCH($B6,Fees!$A$4:$A$9,0))>0,$D6<=INDEX(Fees!$E$4:$E$9,MATCH($B6,Fees!$A$4:$A$9,0))),INDEX(Fees!$D$4:$D$9,MATCH($B6,Fees!$A$4:$A$9,0)),INDEX(Fees!$C$4:$C$9,MATCH($B6,Fees!$A$4:$A$9,0)))+($D6+IF(INDEX(Fees!$G$4:$G$9,MATCH($B6,Fees!$A$4:$A$9,0))="Y",$E6,0))*INDEX(Fees!$F$4:$F$9,MATCH($B6,Fees!$A$4:$A$9,0))),INDEX(Fees!$J$4:$J$9,MATCH($B6,Fees!$A$4:$A$9,0)))) | I6: =IF($B6="","",$D6+$E6-$H6) | J6: =IF($B6="","",$I6-($C6+$F6+$G6)) | K6: =IF(OR($B6="",($C6+$F6+$G6)<=0),"",$J6/($C6+$F6+$G6))
H7: =IF($B7="","",MAX(IF(AND(INDEX(Fees!$H$4:$H$9,MATCH($B7,Fees!$A$4:$A$9,0))>0,$D7<INDEX(Fees!$H$4:$H$9,MATCH($B7,Fees!$A$4:$A$9,0))),INDEX(Fees!$I$4:$I$9,MATCH($B7,Fees!$A$4:$A$9,0)),($D7+IF(INDEX(Fees!$G$4:$G$9,MATCH($B7,Fees!$A$4:$A$9,0))="Y",$E7,0))*INDEX(Fees!$B$4:$B$9,MATCH($B7,Fees!$A$4:$A$9,0))+IF(AND(INDEX(Fees!$E$4:$E$9,MATCH($B7,Fees!$A$4:$A$9,0))>0,$D7<=INDEX(Fees!$E$4:$E$9,MATCH($B7,Fees!$A$4:$A$9,0))),INDEX(Fees!$D$4:$D$9,MATCH($B7,Fees!$A$4:$A$9,0)),INDEX(Fees!$C$4:$C$9,MATCH($B7,Fees!$A$4:$A$9,0)))+($D7+IF(INDEX(Fees!$G$4:$G$9,MATCH($B7,Fees!$A$4:$A$9,0))="Y",$E7,0))*INDEX(Fees!$F$4:$F$9,MATCH($B7,Fees!$A$4:$A$9,0))),INDEX(Fees!$J$4:$J$9,MATCH($B7,Fees!$A$4:$A$9,0)))) | I7: =IF($B7="","",$D7+$E7-$H7) | J7: =IF($B7="","",$I7-($C7+$F7+$G7)) | K7: =IF(OR($B7="",($C7+$F7+$G7)<=0),"",$J7/($C7+$F7+$G7))
H8: =IF($B8="","",MAX(IF(AND(INDEX(Fees!$H$4:$H$9,MATCH($B8,Fees!$A$4:$A$9,0))>0,$D8<INDEX(Fees!$H$4:$H$9,MATCH($B8,Fees!$A$4:$A$9,0))),INDEX(Fees!$I$4:$I$9,MATCH($B8,Fees!$A$4:$A$9,0)),($D8+IF(INDEX(Fees!$G$4:$G$9,MATCH($B8,Fees!$A$4:$A$9,0))="Y",$E8,0))*INDEX(Fees!$B$4:$B$9,MATCH($B8,Fees!$A$4:$A$9,0))+IF(AND(INDEX(Fees!$E$4:$E$9,MATCH($B8,Fees!$A$4:$A$9,0))>0,$D8<=INDEX(Fees!$E$4:$E$9,MATCH($B8,Fees!$A$4:$A$9,0))),INDEX(Fees!$D$4:$D$9,MATCH($B8,Fees!$A$4:$A$9,0)),INDEX(Fees!$C$4:$C$9,MATCH($B8,Fees!$A$4:$A$9,0)))+($D8+IF(INDEX(Fees!$G$4:$G$9,MATCH($B8,Fees!$A$4:$A$9,0))="Y",$E8,0))*INDEX(Fees!$F$4:$F$9,MATCH($B8,Fees!$A$4:$A$9,0))),INDEX(Fees!$J$4:$J$9,MATCH($B8,Fees!$A$4:$A$9,0)))) | I8: =IF($B8="","",$D8+$E8-$H8) | J8: =IF($B8="","",$I8-($C8+$F8+$G8)) | K8: =IF(OR($B8="",($C8+$F8+$G8)<=0),"",$J8/($C8+$F8+$G8))
H9: =IF($B9="","",MAX(IF(AND(INDEX(Fees!$H$4:$H$9,MATCH($B9,Fees!$A$4:$A$9,0))>0,$D9<INDEX(Fees!$H$4:$H$9,MATCH($B9,Fees!$A$4:$A$9,0))),INDEX(Fees!$I$4:$I$9,MATCH($B9,Fees!$A$4:$A$9,0)),($D9+IF(INDEX(Fees!$G$4:$G$9,MATCH($B9,Fees!$A$4:$A$9,0))="Y",$E9,0))*INDEX(Fees!$B$4:$B$9,MATCH($B9,Fees!$A$4:$A$9,0))+IF(AND(INDEX(Fees!$E$4:$E$9,MATCH($B9,Fees!$A$4:$A$9,0))>0,$D9<=INDEX(Fees!$E$4:$E$9,MATCH($B9,Fees!$A$4:$A$9,0))),INDEX(Fees!$D$4:$D$9,MATCH($B9,Fees!$A$4:$A$9,0)),INDEX(Fees!$C$4:$C$9,MATCH($B9,Fees!$A$4:$A$9,0)))+($D9+IF(INDEX(Fees!$G$4:$G$9,MATCH($B9,Fees!$A$4:$A$9,0))="Y",$E9,0))*INDEX(Fees!$F$4:$F$9,MATCH($B9,Fees!$A$4:$A$9,0))),INDEX(Fees!$J$4:$J$9,MATCH($B9,Fees!$A$4:$A$9,0)))) | I9: =IF($B9="","",$D9+$E9-$H9) | J9: =IF($B9="","",$I9-($C9+$F9+$G9)) | K9: =IF(OR($B9="",($C9+$F9+$G9)<=0),"",$J9/($C9+$F9+$G9))
H10: =IF($B10="","",MAX(IF(AND(INDEX(Fees!$H$4:$H$9,MATCH($B10,Fees!$A$4:$A$9,0))>0,$D10<INDEX(Fees!$H$4:$H$9,MATCH($B10,Fees!$A$4:$A$9,0))),INDEX(Fees!$I$4:$I$9,MATCH($B10,Fees!$A$4:$A$9,0)),($D10+IF(INDEX(Fees!$G$4:$G$9,MATCH($B10,Fees!$A$4:$A$9,0))="Y",$E10,0))*INDEX(Fees!$B$4:$B$9,MATCH($B10,Fees!$A$4:$A$9,0))+IF(AND(INDEX(Fees!$E$4:$E$9,MATCH($B10,Fees!$A$4:$A$9,0))>0,$D10<=INDEX(Fees!$E$4:$E$9,MATCH($B10,Fees!$A$4:$A$9,0))),INDEX(Fees!$D$4:$D$9,MATCH($B10,Fees!$A$4:$A$9,0)),INDEX(Fees!$C$4:$C$9,MATCH($B10,Fees!$A$4:$A$9,0)))+($D10+IF(INDEX(Fees!$G$4:$G$9,MATCH($B10,Fees!$A$4:$A$9,0))="Y",$E10,0))*INDEX(Fees!$F$4:$F$9,MATCH($B10,Fees!$A$4:$A$9,0))),INDEX(Fees!$J$4:$J$9,MATCH($B10,Fees!$A$4:$A$9,0)))) | I10: =IF($B10="","",$D10+$E10-$H10) | J10: =IF($B10="","",$I10-($C10+$F10+$G10)) | K10: =IF(OR($B10="",($C10+$F10+$G10)<=0),"",$J10/($C10+$F10+$G10))
H11: =IF($B11="","",MAX(IF(AND(INDEX(Fees!$H$4:$H$9,MATCH($B11,Fees!$A$4:$A$9,0))>0,$D11<INDEX(Fees!$H$4:$H$9,MATCH($B11,Fees!$A$4:$A$9,0))),INDEX(Fees!$I$4:$I$9,MATCH($B11,Fees!$A$4:$A$9,0)),($D11+IF(INDEX(Fees!$G$4:$G$9,MATCH($B11,Fees!$A$4:$A$9,0))="Y",$E11,0))*INDEX(Fees!$B$4:$B$9,MATCH($B11,Fees!$A$4:$A$9,0))+IF(AND(INDEX(Fees!$E$4:$E$9,MATCH($B11,Fees!$A$4:$A$9,0))>0,$D11<=INDEX(Fees!$E$4:$E$9,MATCH($B11,Fees!$A$4:$A$9,0))),INDEX(Fees!$D$4:$D$9,MATCH($B11,Fees!$A$4:$A$9,0)),INDEX(Fees!$C$4:$C$9,MATCH($B11,Fees!$A$4:$A$9,0)))+($D11+IF(INDEX(Fees!$G$4:$G$9,MATCH($B11,Fees!$A$4:$A$9,0))="Y",$E11,0))*INDEX(Fees!$F$4:$F$9,MATCH($B11,Fees!$A$4:$A$9,0))),INDEX(Fees!$J$4:$J$9,MATCH($B11,Fees!$A$4:$A$9,0)))) | I11: =IF($B11="","",$D11+$E11-$H11) | J11: =IF($B11="","",$I11-($C11+$F11+$G11)) | K11: =IF(OR($B11="",($C11+$F11+$G11)<=0),"",$J11/($C11+$F11+$G11))
H12: =IF($B12="","",MAX(IF(AND(INDEX(Fees!$H$4:$H$9,MATCH($B12,Fees!$A$4:$A$9,0))>0,$D12<INDEX(Fees!$H$4:$H$9,MATCH($B12,Fees!$A$4:$A$9,0))),INDEX(Fees!$I$4:$I$9,MATCH($B12,Fees!$A$4:$A$9,0)),($D12+IF(INDEX(Fees!$G$4:$G$9,MATCH($B12,Fees!$A$4:$A$9,0))="Y",$E12,0))*INDEX(Fees!$B$4:$B$9,MATCH($B12,Fees!$A$4:$A$9,0))+IF(AND(INDEX(Fees!$E$4:$E$9,MATCH($B12,Fees!$A$4:$A$9,0))>0,$D12<=INDEX(Fees!$E$4:$E$9,MATCH($B12,Fees!$A$4:$A$9,0))),INDEX(Fees!$D$4:$D$9,MATCH($B12,Fees!$A$4:$A$9,0)),INDEX(Fees!$C$4:$C$9,MATCH($B12,Fees!$A$4:$A$9,0)))+($D12+IF(INDEX(Fees!$G$4:$G$9,MATCH($B12,Fees!$A$4:$A$9,0))="Y",$E12,0))*INDEX(Fees!$F$4:$F$9,MATCH($B12,Fees!$A$4:$A$9,0))),INDEX(Fees!$J$4:$J$9,MATCH($B12,Fees!$A$4:$A$9,0)))) | I12: =IF($B12="","",$D12+$E12-$H12) | J12: =IF($B12="","",$I12-($C12+$F12+$G12)) | K12: =IF(OR($B12="",($C12+$F12+$G12)<=0),"",$J12/($C12+$F12+$G12))
H13: =IF($B13="","",MAX(IF(AND(INDEX(Fees!$H$4:$H$9,MATCH($B13,Fees!$A$4:$A$9,0))>0,$D13<INDEX(Fees!$H$4:$H$9,MATCH($B13,Fees!$A$4:$A$9,0))),INDEX(Fees!$I$4:$I$9,MATCH($B13,Fees!$A$4:$A$9,0)),($D13+IF(INDEX(Fees!$G$4:$G$9,MATCH($B13,Fees!$A$4:$A$9,0))="Y",$E13,0))*INDEX(Fees!$B$4:$B$9,MATCH($B13,Fees!$A$4:$A$9,0))+IF(AND(INDEX(Fees!$E$4:$E$9,MATCH($B13,Fees!$A$4:$A$9,0))>0,$D13<=INDEX(Fees!$E$4:$E$9,MATCH($B13,Fees!$A$4:$A$9,0))),INDEX(Fees!$D$4:$D$9,MATCH($B13,Fees!$A$4:$A$9,0)),INDEX(Fees!$C$4:$C$9,MATCH($B13,Fees!$A$4:$A$9,0)))+($D13+IF(INDEX(Fees!$G$4:$G$9,MATCH($B13,Fees!$A$4:$A$9,0))="Y",$E13,0))*INDEX(Fees!$F$4:$F$9,MATCH($B13,Fees!$A$4:$A$9,0))),INDEX(Fees!$J$4:$J$9,MATCH($B13,Fees!$A$4:$A$9,0)))) | I13: =IF($B13="","",$D13+$E13-$H13) | J13: =IF($B13="","",$I13-($C13+$F13+$G13)) | K13: =IF(OR($B13="",($C13+$F13+$G13)<=0),"",$J13/($C13+$F13+$G13))
H14: =IF($B14="","",MAX(IF(AND(INDEX(Fees!$H$4:$H$9,MATCH($B14,Fees!$A$4:$A$9,0))>0,$D14<INDEX(Fees!$H$4:$H$9,MATCH($B14,Fees!$A$4:$A$9,0))),INDEX(Fees!$I$4:$I$9,MATCH($B14,Fees!$A$4:$A$9,0)),($D14+IF(INDEX(Fees!$G$4:$G$9,MATCH($B14,Fees!$A$4:$A$9,0))="Y",$E14,0))*INDEX(Fees!$B$4:$B$9,MATCH($B14,Fees!$A$4:$A$9,0))+IF(AND(INDEX(Fees!$E$4:$E$9,MATCH($B14,Fees!$A$4:$A$9,0))>0,$D14<=INDEX(Fees!$E$4:$E$9,MATCH($B14,Fees!$A$4:$A$9,0))),INDEX(Fees!$D$4:$D$9,MATCH($B14,Fees!$A$4:$A$9,0)),INDEX(Fees!$C$4:$C$9,MATCH($B14,Fees!$A$4:$A$9,0)))+($D14+IF(INDEX(Fees!$G$4:$G$9,MATCH($B14,Fees!$A$4:$A$9,0))="Y",$E14,0))*INDEX(Fees!$F$4:$F$9,MATCH($B14,Fees!$A$4:$A$9,0))),INDEX(Fees!$J$4:$J$9,MATCH($B14,Fees!$A$4:$A$9,0)))) | I14: =IF($B14="","",$D14+$E14-$H14) | J14: =IF($B14="","",$I14-($C14+$F14+$G14)) | K14: =IF(OR($B14="",($C14+$F14+$G14)<=0),"",$J14/($C14+$F14+$G14))
H15: =IF($B15="","",MAX(IF(AND(INDEX(Fees!$H$4:$H$9,MATCH($B15,Fees!$A$4:$A$9,0))>0,$D15<INDEX(Fees!$H$4:$H$9,MATCH($B15,Fees!$A$4:$A$9,0))),INDEX(Fees!$I$4:$I$9,MATCH($B15,Fees!$A$4:$A$9,0)),($D15+IF(INDEX(Fees!$G$4:$G$9,MATCH($B15,Fees!$A$4:$A$9,0))="Y",$E15,0))*INDEX(Fees!$B$4:$B$9,MATCH($B15,Fees!$A$4:$A$9,0))+IF(AND(INDEX(Fees!$E$4:$E$9,MATCH($B15,Fees!$A$4:$A$9,0))>0,$D15<=INDEX(Fees!$E$4:$E$9,MATCH($B15,Fees!$A$4:$A$9,0))),INDEX(Fees!$D$4:$D$9,MATCH($B15,Fees!$A$4:$A$9,0)),INDEX(Fees!$C$4:$C$9,MATCH($B15,Fees!$A$4:$A$9,0)))+($D15+IF(INDEX(Fees!$G$4:$G$9,MATCH($B15,Fees!$A$4:$A$9,0))="Y",$E15,0))*INDEX(Fees!$F$4:$F$9,MATCH($B15,Fees!$A$4:$A$9,0))),INDEX(Fees!$J$4:$J$9,MATCH($B15,Fees!$A$4:$A$9,0)))) | I15: =IF($B15="","",$D15+$E15-$H15) | J15: =IF($B15="","",$I15-($C15+$F15+$G15)) | K15: =IF(OR($B15="",($C15+$F15+$G15)<=0),"",$J15/($C15+$F15+$G15))
H16: =IF($B16="","",MAX(IF(AND(INDEX(Fees!$H$4:$H$9,MATCH($B16,Fees!$A$4:$A$9,0))>0,$D16<INDEX(Fees!$H$4:$H$9,MATCH($B16,Fees!$A$4:$A$9,0))),INDEX(Fees!$I$4:$I$9,MATCH($B16,Fees!$A$4:$A$9,0)),($D16+IF(INDEX(Fees!$G$4:$G$9,MATCH($B16,Fees!$A$4:$A$9,0))="Y",$E16,0))*INDEX(Fees!$B$4:$B$9,MATCH($B16,Fees!$A$4:$A$9,0))+IF(AND(INDEX(Fees!$E$4:$E$9,MATCH($B16,Fees!$A$4:$A$9,0))>0,$D16<=INDEX(Fees!$E$4:$E$9,MATCH($B16,Fees!$A$4:$A$9,0))),INDEX(Fees!$D$4:$D$9,MATCH($B16,Fees!$A$4:$A$9,0)),INDEX(Fees!$C$4:$C$9,MATCH($B16,Fees!$A$4:$A$9,0)))+($D16+IF(INDEX(Fees!$G$4:$G$9,MATCH($B16,Fees!$A$4:$A$9,0))="Y",$E16,0))*INDEX(Fees!$F$4:$F$9,MATCH($B16,Fees!$A$4:$A$9,0))),INDEX(Fees!$J$4:$J$9,MATCH($B16,Fees!$A$4:$A$9,0)))) | I16: =IF($B16="","",$D16+$E16-$H16) | J16: =IF($B16="","",$I16-($C16+$F16+$G16)) | K16: =IF(OR($B16="",($C16+$F16+$G16)<=0),"",$J16/($C16+$F16+$G16))
... H23: =IF($B23="","",MAX(IF(AND(INDEX(Fees!$H$4:$H$9,MATCH($B23,Fees!$A$4:$A$9,0))>0,$D23<INDEX(Fees!$H$4:$H$9,MATCH($B23,Fees!$A$4:$A$9,0))),INDEX(Fees!$I$4:$I$9,MATCH($B23,Fees!$A$4:$A$9,0)),($D23+IF(INDEX(Fees!$G$4:$G$9,MATCH($B23,Fees!$A$4:$A$9,0))="Y",$E23,0))*INDEX(Fees!$B$4:$B$9,MATCH($B23,Fees!$A$4:$A$9,0))+IF(AND(INDEX(Fees!$E$4:$E$9,MATCH($B23,Fees!$A$4:$A$9,0))>0,$D23<=INDEX(Fees!$E$4:$E$9,MATCH($B23,Fees!$A$4:$A$9,0))),INDEX(Fees!$D$4:$D$9,MATCH($B23,Fees!$A$4:$A$9,0)),INDEX(Fees!$C$4:$C$9,MATCH($B23,Fees!$A$4:$A$9,0)))+($D23+IF(INDEX(Fees!$G$4:$G$9,MATCH($B23,Fees!$A$4:$A$9,0))="Y",$E23,0))*INDEX(Fees!$F$4:$F$9,MATCH($B23,Fees!$A$4:$A$9,0))),INDEX(Fees!$J$4:$J$9,MATCH($B23,Fees!$A$4:$A$9,0)))) | I23: =IF($B23="","",$D23+$E23-$H23) | J23: =IF($B23="","",$I23-($C23+$F23+$G23)) | K23: =IF(OR($B23="",($C23+$F23+$G23)<=0),"",$J23/($C23+$F23+$G23))
A25: TOTAL | J25: =SUM(J4:J23) -> 19.48
